gs_update_utils/__init__.py
gs_update_utils/main.py
gs_update_utils-1.0.4.dist-info/LICENSE
gs_update_utils-1.0.4.dist-info/METADATA
gs_update_utils-1.0.4.dist-info/WHEEL
gs_update_utils-1.0.4.dist-info/top_level.txt
gs_update_utils-1.0.4.dist-info/RECORD
