Metadata-Version: 2.1
Name: gs-update-utils
Version: 1.0.4
Summary: Utilities for working with Google Sheets: establishing a connection, reading data from a sheet, and uploading a DataFrame to Google Sheets with retry support.
Author: xgzx
Author-email: vadijimory@gmail.com
Keywords: example python
Classifier: Programming Language :: Python :: 3.11
Classifier: License :: OSI Approved :: MIT License
Classifier: Operating System :: OS Independent
Requires-Python: >=3.7
License-File: LICENSE
Requires-Dist: pandas
Requires-Dist: gspread
Requires-Dist: gspread-dataframe
